odoo/addons/sm_lopd/__init__.py
odoo/addons/sm_lopd/__manifest__.py
odoo/addons/sm_lopd/email_tmpl/lopd_companies_template.xml
odoo/addons/sm_lopd/email_tmpl/lopd_email.xml
odoo/addons/sm_lopd/models/__init__.py
odoo/addons/sm_lopd/models/models_sm_company.py
odoo/addons/sm_lopd/models/models_sm_lopd_cron.py
odoo/addons/sm_lopd/models/models_sm_member.py
odoo/addons/sm_lopd/models/models_sm_res_config_settings.py
odoo/addons/sm_lopd/report/lopd_report.xml
odoo/addons/sm_lopd/security/ir.model.access.csv
odoo/addons/sm_lopd/static/src/img/logo-firma.png
odoo/addons/sm_lopd/views/views_cron.xml
odoo/addons/sm_lopd/views/views_members.xml
odoo/addons/sm_lopd/views/views_res_config_settings.xml
odoo11_addon_sm_lopd-11.0.0.0.2.dist-info/METADATA
odoo11_addon_sm_lopd-11.0.0.0.2.dist-info/WHEEL
odoo11_addon_sm_lopd-11.0.0.0.2.dist-info/top_level.txt
odoo11_addon_sm_lopd-11.0.0.0.2.dist-info/RECORD
